Metadata-Version: 1.0
Name: PyDMTQ
Version: 0.0.3
Summary: Python Interface For DMTQ API
Home-page: https://github.com/Naville/DMTQResearch
Author: Naville
Author-email: admin@mayuyu.io
License: GPL
Platform: UNKNOWN
